{"y26111A": {"ID": "u294370447", "product_name": "D★良品♪ZX-10R('04～'05) K-FACTORY 4-2-1 チタンエキゾーストパイプ♪54mm♪", "price": "35800", "start_time": "2020-04-06 23:43:55", "end_time": "2020-04-07 08:37:00", "src": "https://auctions.c.yimg.jp/images.auctions.yahoo.co.jp/image/dr000/auc0508/users/61b9fb41fab22e8dd0e5441cc2acb80024595b55/i-img600x450-1565664828i8hb5m226.jpg", "access": "0", "watch": "15", "detail_URL": "https://page.auctions.yahoo.co.jp/jp/auction/u294370447", "relist_url": "https://auctions.yahoo.co.jp/pageinfo16/jp/show/resubmit?aID=u294370447"}, "T11ZM41": {"ID": "o254303048", "product_name": "★M）良品♪GSX-R1100(GV73A) 純正 右スイッチ&スロットル♪実働車取外♪", "price": "3480", "start_time": "2020-04-05 19:22:28", "end_time": "2020-04-07 08:36:25", "src": "https://auctions.c.yimg.jp/images.auctions.yahoo.co.jp/image/dr274/auc0408/users/7/8/4/0/mukeidou-imgbatch_1533685648/600x450-2018080200322.jpg", "access": "0", "watch": "4", "detail_URL": "https://page.auctions.yahoo.co.jp/jp/auction/o254303048", "relist_url": "https://auctions.yahoo.co.jp/pageinfo23/jp/show/resubmit?aID=o254303048"}, "T11BD59": {"ID": "x685307726", "product_name": "★『S』良品♪ZX-12R ヨシムラ デジタルマルチメーター♪油温センサーボルト付♪", "price": "9980", "start_time": "2020-04-05 20:24:06", "end_time": "2020-04-07 01:24:51", "src": "https://auctions.c.yimg.jp/images.auctions.yahoo.co.jp/image/dr000/auc0103/users/936e6f3f69d1730e2ed6e42e1e499ecc06b9bdad/i-img600x450-15843351331vtnkz806999.jpg", "access": "0", "watch": "6", "detail_URL": "https://page.auctions.yahoo.co.jp/jp/auction/x685307726", "relist_url": "https://auctions.yahoo.co.jp/pageinfo19/jp/show/resubmit?aID=x685307726"}, "T12GF23": {"ID": "d348886772", "product_name": "★M）良品♪GSX-R750('86) 純正ステップset♪実働車取外♪", "price": "6980", "start_time": "2020-04-05 17:42:32", "end_time": "2020-04-06 23:53:40", "src": "https://auctions.c.yimg.jp/images.auctions.yahoo.co.jp/image/dr000/auc0502/users/61b9fb41fab22e8dd0e5441cc2acb80024595b55/i-img600x450-15513142767mwyxi7695.jpg", "access": "0", "watch": "3", "detail_URL": "https://page.auctions.yahoo.co.jp/jp/auction/d348886772", "relist_url": "https://auctions.yahoo.co.jp/pageinfo4/jp/show/resubmit?aID=d348886772"}, "AY26102A/B": {"ID": "d403978351", "product_name": "★【M3】良品♪CB400SF-Revo(EBL-NC42) アールズギア ワイバン 手曲げ Oval フルチタンマフラー♪", "price": "82800", "start_time": "2020-04-06 23:46:57", "end_time": "2020-04-06 23:52:23", "src": "https://auctions.c.yimg.jp/images.auctions.yahoo.co.jp/image/dr000/auc0511/users/936e6f3f69d1730e2ed6e42e1e499ecc06b9bdad/i-img600x450-1574757105cwa3a2383211.jpg", "access": "0", "watch": "24", "detail_URL": "https://page.auctions.yahoo.co.jp/jp/auction/d403978351", "relist_url": "https://auctions.yahoo.co.jp/pageinfo4/jp/show/resubmit?aID=d403978351"}}